dbt_lineage/__init__.py
dbt_lineage/cli.py
dbt_lineage/default_config.yml
dbt_lineage/graph.py
dbt_lineage/palettes.py
dbt_lineage/settings.py
dbt_lineage-0.0.3.dist-info/WHEEL
dbt_lineage-0.0.3.dist-info/METADATA
dbt_lineage-0.0.3.dist-info/entry_points.txt
dbt_lineage-0.0.3.dist-info/RECORD
