Metadata-Version: 2.1
Name: dbt-lineage
Version: 0.0.3
Summary: 
Author: Felipe Aguirre Martinez
Author-email: felipea@kometsales.com
Requires-Python: >=3.7,<4.0
Classifier: Programming Language :: Python :: 3
Classifier: Programming Language :: Python :: 3.7
Classifier: Programming Language :: Python :: 3.8
Classifier: Programming Language :: Python :: 3.9
Classifier: Programming Language :: Python :: 3.10
Classifier: Programming Language :: Python :: 3.11
Requires-Dist: graphviz (>=0.20.1,<0.21.0)
Requires-Dist: omegaconf (>=2.3.0,<3.0.0)
Requires-Dist: typer (>=0.6.1,<0.7.0)
